{

  "module": {
    "wheelDiameterInches": 4.0,
    "driveGearRatio": 6.75,
    "turningGearRatio": 21.4285714286,
    "turningKP": 0.5
  },
  "dimensions": {
    "trackWidthInches": 21.875,
    "wheelBaseInches": 21.875
  },
  "motors": {
    "drive": {
      "frontLeft": 3,
      "frontRight": 2,
      "backLeft": 4,
      "backRight": 1
    },
    "turning": {
      "frontLeft": 7,
      "frontRight": 6,
      "backLeft": 8,
      "backRight": 5
    }
  },
  "encoders": {
    "absolutePorts": {
      "frontLeft": 3,
      "frontRight": 2,
      "backLeft": 4,
      "backRight": 1
    },
    "absoluteOffsetsRad": {
      "frontLeft": 3.298261,
      "frontRight": 3.876267,
      "backLeft": -2.186846,
      "backRight": 2.496463
    },
    "driveReversed": {
      "frontLeft": false,
      "frontRight": false,
      "backLeft": false,
      "backRight": false
    },
    "turningReversed": {
      "frontLeft": false,
      "frontRight": false,
      "backLeft": false,
      "backRight": false
    },
    "absoluteReversed": {
      "frontLeft": false,
      "frontRight": false,
      "backLeft": false,
      "backRight": false
    }
  },
  "limits": {
    "maxSpeedMps": 5.0,
    "maxAngularSpeedRadPerSec": 12.566,
    "teleopSpeedScale": 0.25
  }
}
